{"v":"5.5.2","meta":{"a":"SVGator","d":"SVGator, the ultimate SVG animation generator now supports Lottie: a thoughtfully designed, intuitive interface, right at your fingertips.","g":"Made in SVGator (https://www.svgator.com/)","tc":""},"metadata":{"filename":"A.I. Based Consumer Insights.json","customProps":{"k":["SVGator","svgator","lottie animation","svg animation","lottie","svg"],"version":1,"app":"https://app.svgator.com/","site":"https://www.svgator.com/","date":"2024-03-29T09:02:23.451Z"}},"nm":"A.I. Based Consumer Insights","ddd":0,"assets":[],"w":1200,"h":1200,"ip":0,"op":340,"fr":100,"fonts":{"list":[]},"layers":[{"ty":4,"st":0,"ip":0,"op":340,"ks":{"a":{"a":0,"k":[540.000015,539.999969]},"p":{"a":0,"k":[600,600]}},"shapes":[{"ty":"gr","it":[{"ty":"gr","it":[{"ty":"sh","ks":{"a":0,"k":{"v":[[763.7,762.2],[811.4,584.6],[633.8,536.9],[586.1,714.5],[763.7,762.2]],"i":[[0,0],[35.8,62.2],[62.2,-35.9],[-35.8,-62.2],[-62.2,35.9]],"o":[[62.2,-35.9],[-35.9,-62.2],[-62.2,35.9],[35.9,62.2],[0,0]],"c":false}},"ln":"ef9a2VuAmdn147"},{"ty":"fl","o":{"a":0,"k":100},"c":{"a":0,"k":[0,0.682353,1]},"ln":"ef9a2VuAmdn148"},{"ty":"tr","o":{"a":0,"k":100},"a":{"a":0,"k":[698.75,649.549988]},"p":{"a":0,"k":[698.75,649.549988]}}],"ln":"ef9a2VuAmdn146"},{"ty":"gr","it":[{"ty":"sh","ks":{"a":0,"k":{"v":[[763.7,543.1],[811.4,365.5],[633.8,317.8],[586.1,495.4],[763.7,543.1]],"i":[[0,0],[35.8,62.2],[62.2,-35.8],[-35.8,-62.2],[-62.2,35.9]],"o":[[62.2,-35.9],[-35.9,-62.2],[-62.2,35.9],[35.9,62.2],[0,0]],"c":false}},"ln":"ef9a2VuAmdn144"},{"ty":"fl","o":{"a":0,"k":100},"c":{"a":1,"k":[{"t":0,"s":[0,0.819608,0.780392],"i":{"x":1,"y":1},"o":{"x":0,"y":0}},{"t":110,"s":[0,0.819608,0.780392],"i":{"x":1,"y":1},"o":{"x":0,"y":0}},{"t":150,"s":[0.698039,0.945098,0.933333],"i":{"x":1,"y":1},"o":{"x":0,"y":0}},{"t":190,"s":[0,0.819608,0.780392],"i":{"x":1,"y":1},"o":{"x":0,"y":0}},{"t":300,"s":[0,0.819608,0.780392],"i":{"x":1,"y":1},"o":{"x":0,"y":0}}]},"ln":"ef9a2VuAmdn145"},{"ty":"tr","o":{"a":0,"k":100},"a":{"a":0,"k":[698.750031,430.472214]},"p":{"a":0,"k":[698.750031,430.472214]}}],"ln":"ef9a2VuAmdn143"},{"ty":"gr","it":[{"ty":"sh","ks":{"a":0,"k":{"v":[[901.1,456.7],[948.8,279.1],[771.2,231.4],[723.5,409],[901.1,456.7]],"i":[[0,0],[35.8,62.2],[62.2,-35.8],[-35.8,-62.2],[-62.1,35.9]],"o":[[62.2,-35.9],[-35.9,-62.2],[-62.2,35.9],[35.9,62.2],[0,0]],"c":false}},"ln":"ef9a2VuAmdn141"},{"ty":"fl","o":{"a":0,"k":100},"c":{"a":1,"k":[{"t":0,"s":[0,0.682353,1],"i":{"x":1,"y":1},"o":{"x":0,"y":0}},{"t":170,"s":[0,0.682353,1],"i":{"x":1,"y":1},"o":{"x":0,"y":0}},{"t":210,"s":[0.698039,0.905882,1],"i":{"x":1,"y":1},"o":{"x":0,"y":0}},{"t":250,"s":[0,0.682353,1],"i":{"x":1,"y":1},"o":{"x":0,"y":0}},{"t":300,"s":[0,0.682353,1],"i":{"x":1,"y":1},"o":{"x":0,"y":0}}]},"ln":"ef9a2VuAmdn142"},{"ty":"tr","o":{"a":0,"k":100},"a":{"a":0,"k":[836.149994,344.07222]},"p":{"a":0,"k":[836.149994,344.07222]}}],"ln":"ef9a2VuAmdn140"},{"ty":"gr","it":[{"ty":"sh","ks":{"a":0,"k":{"v":[[974.9,653.4],[1022.6,475.8],[845,428.1],[797.3,605.7],[974.9,653.4]],"i":[[0,0],[35.8,62.2],[62.2,-35.8],[-35.8,-62.2],[-62.2,35.9]],"o":[[62.2,-35.9],[-35.9,-62.2],[-62.2,35.9],[35.9,62.3],[0,0]],"c":false}},"ln":"ef9a2VuAmdn138"},{"ty":"fl","o":{"a":0,"k":100},"c":{"a":1,"k":[{"t":0,"s":[0,0.819608,0.780392],"i":{"x":1,"y":1},"o":{"x":0,"y":0}},{"t":20,"s":[0,0.819608,0.780392],"i":{"x":1,"y":1},"o":{"x":0,"y":0}},{"t":60,"s":[0.698039,0.945098,0.933333],"i":{"x":1,"y":1},"o":{"x":0,"y":0}},{"t":100,"s":[0,0.819608,0.780392],"i":{"x":1,"y":1},"o":{"x":0,"y":0}},{"t":300,"s":[0,0.819608,0.780392],"i":{"x":1,"y":1},"o":{"x":0,"y":0}}]},"ln":"ef9a2VuAmdn139"},{"ty":"tr","o":{"a":0,"k":100},"a":{"a":0,"k":[909.950012,540.783127]},"p":{"a":0,"k":[909.950012,540.783127]}}],"ln":"ef9a2VuAmdn137"},{"ty":"gr","it":[{"ty":"sh","ks":{"a":0,"k":{"v":[[763.7,324],[811.4,146.4],[633.8,98.7],[586.1,276.3],[763.7,324]],"i":[[0,0],[35.8,62.2],[62.2,-35.9],[-35.8,-62.2],[-62.2,35.8]],"o":[[62.2,-35.9],[-35.9,-62.2],[-62.2,35.9],[35.9,62.2],[0,0]],"c":false}},"ln":"ef9a2VuAmdn135"},{"ty":"fl","o":{"a":0,"k":100},"c":{"a":1,"k":[{"t":0,"s":[0,0.682353,1],"i":{"x":1,"y":1},"o":{"x":0,"y":0}},{"t":90,"s":[0,0.682353,1],"i":{"x":1,"y":1},"o":{"x":0,"y":0}},{"t":130,"s":[0.698039,0.905882,1],"i":{"x":1,"y":1},"o":{"x":0,"y":0}},{"t":170,"s":[0,0.682353,1],"i":{"x":1,"y":1},"o":{"x":0,"y":0}},{"t":300,"s":[0,0.682353,1],"i":{"x":1,"y":1},"o":{"x":0,"y":0}}]},"ln":"ef9a2VuAmdn136"},{"ty":"tr","o":{"a":0,"k":100},"a":{"a":0,"k":[698.75,211.327774]},"p":{"a":0,"k":[698.75,211.327774]}}],"ln":"ef9a2VuAmdn134"},{"ty":"gr","it":[{"ty":"sh","ks":{"a":0,"k":{"v":[[901.1,854.3],[948.8,676.7],[771.2,629],[723.5,806.6],[901.1,854.3]],"i":[[0,0],[35.8,62.2],[62.2,-35.9],[-35.8,-62.2],[-62.1,35.8]],"o":[[62.2,-35.9],[-35.8,-62.2],[-62.2,35.9],[35.9,62.2],[0,0]],"c":false}},"ln":"ef9a2VuAmdn132"},{"ty":"fl","o":{"a":0,"k":100},"c":{"a":1,"k":[{"t":0,"s":[0,0.682353,1],"i":{"x":1,"y":1},"o":{"x":0,"y":0}},{"t":190,"s":[0,0.682353,1],"i":{"x":1,"y":1},"o":{"x":0,"y":0}},{"t":230,"s":[0.698039,0.905882,1],"i":{"x":1,"y":1},"o":{"x":0,"y":0}},{"t":270,"s":[0,0.682353,1],"i":{"x":1,"y":1},"o":{"x":0,"y":0}},{"t":300,"s":[0,0.682353,1],"i":{"x":1,"y":1},"o":{"x":0,"y":0}}]},"ln":"ef9a2VuAmdn133"},{"ty":"tr","o":{"a":0,"k":100},"a":{"a":0,"k":[836.149994,741.627747]},"p":{"a":0,"k":[836.149994,741.627747]}}],"ln":"ef9a2VuAmdn131"},{"ty":"gr","it":[{"ty":"sh","ks":{"a":0,"k":{"v":[[763.7,981.3],[811.4,803.7],[633.8,756],[586.1,933.6],[763.7,981.3]],"i":[[0,0],[35.8,62.2],[62.2,-35.8],[-35.8,-62.2],[-62.2,35.9]],"o":[[62.2,-35.9],[-35.9,-62.2],[-62.2,35.9],[35.9,62.2],[0,0]],"c":false}},"ln":"ef9a2VuAmdn129"},{"ty":"fl","o":{"a":0,"k":100},"c":{"a":1,"k":[{"t":0,"s":[0,0.819608,0.780392],"i":{"x":1,"y":1},"o":{"x":0,"y":0}},{"t":80,"s":[0,0.819608,0.780392],"i":{"x":1,"y":1},"o":{"x":0,"y":0}},{"t":120,"s":[0.698039,0.945098,0.933333],"i":{"x":1,"y":1},"o":{"x":0,"y":0}},{"t":160,"s":[0,0.819608,0.780392],"i":{"x":1,"y":1},"o":{"x":0,"y":0}},{"t":300,"s":[0,0.819608,0.780392],"i":{"x":1,"y":1},"o":{"x":0,"y":0}}]},"ln":"ef9a2VuAmdn130"},{"ty":"tr","o":{"a":0,"k":100},"a":{"a":0,"k":[698.75,868.672211]},"p":{"a":0,"k":[698.75,868.672211]}}],"ln":"ef9a2VuAmdn128"},{"ty":"gr","it":[{"ty":"sh","ks":{"a":0,"k":{"v":[[316.3,317.8],[268.6,495.4],[446.2,543.1],[493.9,365.5],[316.3,317.8]],"i":[[0,0],[-35.8,-62.2],[-62.2,35.9],[35.8,62.2],[62.2,-35.9]],"o":[[-62.2,35.9],[35.9,62.2],[62.2,-35.9],[-35.9,-62.2],[0,0]],"c":false}},"ln":"ef9a2VuAmdn126"},{"ty":"fl","o":{"a":0,"k":100},"c":{"a":1,"k":[{"t":0,"s":[0,0.819608,0.780392],"i":{"x":1,"y":1},"o":{"x":0,"y":0}},{"t":40,"s":[0.698039,0.945098,0.933333],"i":{"x":1,"y":1},"o":{"x":0,"y":0}},{"t":90,"s":[0,0.819608,0.780392],"i":{"x":1,"y":1},"o":{"x":0,"y":0}},{"t":300,"s":[0,0.819608,0.780392],"i":{"x":1,"y":1},"o":{"x":0,"y":0}}]},"ln":"ef9a2VuAmdn127"},{"ty":"tr","o":{"a":0,"k":100},"a":{"a":0,"k":[381.249985,430.450012]},"p":{"a":0,"k":[381.249985,430.450012]}}],"ln":"ef9a2VuAmdn125"},{"ty":"gr","it":[{"ty":"sh","ks":{"a":0,"k":{"v":[[316.3,536.9],[268.6,714.5],[446.2,762.2],[493.9,584.6],[316.3,536.9]],"i":[[0,0],[-35.8,-62.2],[-62.2,35.8],[35.8,62.2],[62.2,-35.9]],"o":[[-62.2,35.9],[35.9,62.2],[62.2,-35.9],[-35.9,-62.2],[0,0]],"c":false}},"ln":"ef9a2VuAmdn123"},{"ty":"fl","o":{"a":0,"k":100},"c":{"a":1,"k":[{"t":0,"s":[0,0.682353,1],"i":{"x":1,"y":1},"o":{"x":0,"y":0}},{"t":130,"s":[0,0.682353,1],"i":{"x":1,"y":1},"o":{"x":0,"y":0}},{"t":180,"s":[0.698039,0.905882,1],"i":{"x":1,"y":1},"o":{"x":0,"y":0}},{"t":230,"s":[0,0.682353,1],"i":{"x":1,"y":1},"o":{"x":0,"y":0}},{"t":300,"s":[0,0.682353,1],"i":{"x":1,"y":1},"o":{"x":0,"y":0}}]},"ln":"ef9a2VuAmdn124"},{"ty":"tr","o":{"a":0,"k":100},"a":{"a":0,"k":[381.249985,649.527771]},"p":{"a":0,"k":[381.249985,649.527771]}}],"ln":"ef9a2VuAmdn122"},{"ty":"gr","it":[{"ty":"sh","ks":{"a":0,"k":{"v":[[316.3,756],[268.6,933.6],[446.2,981.3],[493.9,803.7],[316.3,756]],"i":[[0,0],[-35.8,-62.2],[-62.2,35.8],[35.8,62.2],[62.2,-35.8]],"o":[[-62.2,35.9],[35.9,62.2],[62.2,-35.9],[-35.9,-62.2],[0,0]],"c":false}},"ln":"ef9a2VuAmdn120"},{"ty":"fl","o":{"a":0,"k":100},"c":{"a":1,"k":[{"t":0,"s":[0,0.819608,0.780392],"i":{"x":1,"y":1},"o":{"x":0,"y":0}},{"t":30,"s":[0,0.819608,0.780392],"i":{"x":1,"y":1},"o":{"x":0,"y":0}},{"t":70,"s":[0.698039,0.945098,0.933333],"i":{"x":1,"y":1},"o":{"x":0,"y":0}},{"t":110,"s":[0,0.819608,0.780392],"i":{"x":1,"y":1},"o":{"x":0,"y":0}},{"t":300,"s":[0,0.819608,0.780392],"i":{"x":1,"y":1},"o":{"x":0,"y":0}}]},"ln":"ef9a2VuAmdn121"},{"ty":"tr","o":{"a":0,"k":100},"a":{"a":0,"k":[381.249985,868.649994]},"p":{"a":0,"k":[381.249985,868.649994]}}],"ln":"ef9a2VuAmdn119"},{"ty":"gr","it":[{"ty":"sh","ks":{"a":0,"k":{"v":[[178.9,627.4],[131.2,805],[308.8,852.7],[356.5,675.1],[178.9,627.4]],"i":[[0,0],[-35.8,-62.2],[-62.2,35.8],[35.8,62.2],[62.2,-35.9]],"o":[[-62.2,35.9],[35.9,62.2],[62.2,-35.9],[-35.9,-62.2],[0,0]],"c":false}},"ln":"ef9a2VuAmdn117"},{"ty":"fl","o":{"a":0,"k":100},"c":{"a":0,"k":[0,0.819608,0.780392]},"ln":"ef9a2VuAmdn118"},{"ty":"tr","o":{"a":0,"k":100},"a":{"a":0,"k":[243.849998,740.027771]},"p":{"a":0,"k":[243.849998,740.027771]}}],"ln":"ef9a2VuAmdn116"},{"ty":"gr","it":[{"ty":"sh","ks":{"a":0,"k":{"v":[[105.1,430.7],[57.4,608.3],[235,656],[282.7,478.4],[105.1,430.7]],"i":[[0,0],[-35.8,-62.2],[-62.2,35.8],[35.8,62.2],[62.2,-35.9]],"o":[[-62.2,35.9],[35.9,62.2],[62.2,-35.9],[-35.9,-62.3],[0,0]],"c":false}},"ln":"ef9a2VuAmdn114"},{"ty":"fl","o":{"a":0,"k":100},"c":{"a":1,"k":[{"t":0,"s":[0,0.682353,1],"i":{"x":1,"y":1},"o":{"x":0,"y":0}},{"t":170,"s":[0,0.682353,1],"i":{"x":1,"y":1},"o":{"x":0,"y":0}},{"t":210,"s":[0.698039,0.905882,1],"i":{"x":1,"y":1},"o":{"x":0,"y":0}},{"t":250,"s":[0,0.682353,1],"i":{"x":1,"y":1},"o":{"x":0,"y":0}},{"t":300,"s":[0,0.682353,1],"i":{"x":1,"y":1},"o":{"x":0,"y":0}}]},"ln":"ef9a2VuAmdn115"},{"ty":"tr","o":{"a":0,"k":100},"a":{"a":0,"k":[170.050003,543.316879]},"p":{"a":0,"k":[170.050003,543.316879]}}],"ln":"ef9a2VuAmdn113"},{"ty":"gr","it":[{"ty":"sh","ks":{"a":0,"k":{"v":[[178.9,229.9],[131.2,407.5],[308.8,455.2],[356.5,277.6],[178.9,229.9]],"i":[[0,0],[-35.8,-62.2],[-62.2,35.8],[35.8,62.2],[62.2,-35.9]],"o":[[-62.2,35.9],[35.9,62.2],[62.2,-35.9],[-35.9,-62.3],[0,0]],"c":false}},"ln":"ef9a2VuAmdn111"},{"ty":"fl","o":{"a":0,"k":100},"c":{"a":1,"k":[{"t":0,"s":[0,0.819608,0.780392],"i":{"x":1,"y":1},"o":{"x":0,"y":0}},{"t":60,"s":[0,0.819608,0.780392],"i":{"x":1,"y":1},"o":{"x":0,"y":0}},{"t":100,"s":[0.698039,0.945098,0.933333],"i":{"x":1,"y":1},"o":{"x":0,"y":0}},{"t":140,"s":[0,0.819608,0.780392],"i":{"x":1,"y":1},"o":{"x":0,"y":0}},{"t":300,"s":[0,0.819608,0.780392],"i":{"x":1,"y":1},"o":{"x":0,"y":0}}]},"ln":"ef9a2VuAmdn112"},{"ty":"tr","o":{"a":0,"k":100},"a":{"a":0,"k":[243.849998,342.516891]},"p":{"a":0,"k":[243.849998,342.516891]}}],"ln":"ef9a2VuAmdn110"},{"ty":"gr","it":[{"ty":"sh","ks":{"a":0,"k":{"v":[[316.3,98.7],[268.6,276.3],[446.2,324],[493.9,146.4],[316.3,98.7]],"i":[[0,0],[-35.8,-62.2],[-62.2,35.8],[35.8,62.2],[62.2,-35.9]],"o":[[-62.2,35.9],[35.9,62.2],[62.2,-35.9],[-35.9,-62.2],[0,0]],"c":false}},"ln":"ef9a2VuAmdn18"},{"ty":"fl","o":{"a":0,"k":100},"c":{"a":1,"k":[{"t":0,"s":[0,0.682353,1],"i":{"x":1,"y":1},"o":{"x":0,"y":0}},{"t":220,"s":[0,0.682353,1],"i":{"x":1,"y":1},"o":{"x":0,"y":0}},{"t":260,"s":[0.698039,0.905882,1],"i":{"x":1,"y":1},"o":{"x":0,"y":0}},{"t":300,"s":[0,0.682353,1],"i":{"x":1,"y":1},"o":{"x":0,"y":0}}]},"ln":"ef9a2VuAmdn19"},{"ty":"tr","o":{"a":0,"k":100},"a":{"a":0,"k":[381.249985,211.327774]},"p":{"a":0,"k":[381.249985,211.327774]}}],"ln":"ef9a2VuAmdn17"},{"ty":"tr","o":{"a":0,"k":100}}],"ln":"ef9a2VuAmdn16"}],"ln":"ef9a2VuAmdn15"},{"ty":4,"st":0,"ip":0,"op":340,"ks":{"a":{"a":0,"k":[557.413249,547.949526]},"p":{"a":0,"k":[-5555345.001751,-5461016.560474]}},"shapes":[{"ty":"rc","p":{"a":0,"k":[5556502.415,5462164.51]},"s":{"a":0,"k":[11113004.83,10924329.02]},"r":{"a":0,"k":0},"ln":"ef9a2VuAmdn13"},{"ty":"fl","o":{"a":0,"k":100},"c":{"a":0,"k":[0.956863,0.960784,0.964706]},"ln":"ef9a2VuAmdn14"}],"ln":"ef9a2VuAmdn12"}]}